ctu_time/__init__.py
ctu_time/ctu.py
ctu_time-1.0.0.dist-info/LICENSE
ctu_time-1.0.0.dist-info/METADATA
ctu_time-1.0.0.dist-info/WHEEL
ctu_time-1.0.0.dist-info/RECORD
