Metadata-Version: 2.3
Name: ctu_time
Version: 1.0.0
Summary: CTU - Calculated Time Uncoordinated. Hyperlocal. No timezones. No DST. For Humans.
License: MIT
Author: Anselm Kiefner
Author-email: ctu-github@anselm.kiefner.de
Requires-Python: >=3.9
Classifier: License :: OSI Approved :: MIT License
Classifier: Programming Language :: Python :: 3
Classifier: Programming Language :: Python :: 3.9
Classifier: Programming Language :: Python :: 3.10
Classifier: Programming Language :: Python :: 3.11
Classifier: Programming Language :: Python :: 3.12
Classifier: Programming Language :: Python :: 3.13
